{
  "_note1": "KEEP THIS FILE! Check it into a version control system (VCS) like git.",
  "_note2": "ObjectBox manages crucial IDs for your object model. See docs for details.",
  "_note3": "If you have VCS merge conflicts, you must resolve them according to ObjectBox docs.",
  "entities": [
    {
      "id": "1:7226041707148712205",
      "lastPropertyId": "4:7027513641316469434",
      "name": "ConfShops",
      "properties": [
        {
          "id": "1:8824521804848718353",
          "name": "id",
          "type": 6,
          "flags": 1
        },
        {
          "id": "2:2111520568564295165",
          "name": "fixedAmount",
          "type": 1
        },
        {
          "id": "3:1797559342325174756",
          "name": "tip",
          "type": 1
        },
        {
          "id": "4:7027513641316469434",
          "name": "service",
          "type": 1
        }
      ],
      "relations": [
        {
          "id": "1:8553315540855453725",
          "name": "shop",
          "targetId": "6:4955514230935774485"
        }
      ]
    },
    {
      "id": "2:4270968864036470725",
      "lastPropertyId": "3:3549955664932321262",
      "name": "Config",
      "properties": [
        {
          "id": "1:3156097040061609740",
          "name": "id",
          "type": 6,
          "flags": 1
        },
        {
          "id": "2:7027043221350984322",
          "name": "parameter",
          "type": 9,
          "flags": 8,
          "indexId": "1:8808474503948147209"
        },
        {
          "id": "3:3549955664932321262",
          "name": "value",
          "type": 9
        }
      ],
      "relations": []
    },
    {
      "id": "3:1170452095038697030",
      "lastPropertyId": "1:2395830314590597627",
      "name": "Configure",
      "properties": [
        {
          "id": "1:2395830314590597627",
          "name": "id",
          "type": 6,
          "flags": 1
        }
      ],
      "relations": []
    },
    {
      "id": "4:8838836156563474517",
      "lastPropertyId": "3:4614818150808207134",
      "name": "Device",
      "properties": [
        {
          "id": "1:6044749479983758094",
          "name": "id",
          "type": 6,
          "flags": 1
        },
        {
          "id": "2:1470597563572463354",
          "name": "serie",
          "type": 9
        },
        {
          "id": "3:4614818150808207134",
          "name": "historyId",
          "type": 11,
          "flags": 520,
          "indexId": "2:7508026259719075340",
          "relationTarget": "History"
        }
      ],
      "relations": []
    },
    {
      "id": "5:4550954014715653921",
      "lastPropertyId": "1:503171310307881311",
      "name": "History",
      "properties": [
        {
          "id": "1:503171310307881311",
          "name": "id",
          "type": 6,
          "flags": 1
        }
      ],
      "relations": []
    },
    {
      "id": "6:4955514230935774485",
      "lastPropertyId": "8:7050491115795440333",
      "name": "Shop",
      "properties": [
        {
          "id": "1:2569121509188349649",
          "name": "id",
          "type": 6,
          "flags": 1
        },
        {
          "id": "2:2448053765938514520",
          "name": "codigo",
          "type": 9
        },
        {
          "id": "3:5515433041696038067",
          "name": "giro",
          "type": 9
        },
        {
          "id": "4:3976408049744472978",
          "name": "name",
          "type": 9
        },
        {
          "id": "5:5117889947730984183",
          "name": "direction",
          "type": 9
        },
        {
          "id": "6:1136400180579772093",
          "name": "phone",
          "type": 9
        },
        {
          "id": "7:4306759906828667758",
          "name": "historyId",
          "type": 11,
          "flags": 520,
          "indexId": "3:4515511116789690400",
          "relationTarget": "History"
        },
        {
          "id": "8:7050491115795440333",
          "name": "confshopId",
          "type": 11,
          "flags": 520,
          "indexId": "4:9191098613801237017",
          "relationTarget": "ConfShops"
        }
      ],
      "relations": []
    },
    {
      "id": "7:430569070135028100",
      "lastPropertyId": "1:4139957377534748283",
      "name": "Variables",
      "properties": [
        {
          "id": "1:4139957377534748283",
          "name": "id",
          "type": 6,
          "flags": 1
        }
      ],
      "relations": []
    }
  ],
  "lastEntityId": "7:430569070135028100",
  "lastIndexId": "4:9191098613801237017",
  "lastRelationId": "1:8553315540855453725",
  "lastSequenceId": "0:0",
  "modelVersion": 5,
  "modelVersionParserMinimum": 5,
  "retiredEntityUids": [],
  "retiredIndexUids": [],
  "retiredPropertyUids": [],
  "retiredRelationUids": [],
  "version": 1
}